usaugment/__about__.py
usaugment/__init__.py
usaugment/albumentations/__init__.py
usaugment/albumentations/depth_attenuation.py
usaugment/albumentations/gaussian_shadow.py
usaugment/albumentations/haze_artifact.py
usaugment/albumentations/speckle_reduction.py
usaugment-1.0.1.dist-info/METADATA
usaugment-1.0.1.dist-info/WHEEL
usaugment-1.0.1.dist-info/licenses/LICENSE
usaugment-1.0.1.dist-info/RECORD
