Metadata-Version: 2.4
Name: usaugment
Version: 1.0.1
Summary: Ultrasound-specific image transforms for training deep neural networks.
Project-URL: Homepage, https://github.com/adamtupper/usaugment
Project-URL: Documentation, https://github.com/adamtupper/usaugment/wiki
Project-URL: Issues, https://github.com/adamtupper/usaugment/issues
Author-email: Adam Tupper <adam.tupper.1@ulaval.ca>
License-File: LICENSE
Classifier: License :: OSI Approved :: MIT License
Classifier: Operating System :: OS Independent
Classifier: Programming Language :: Python :: 3
Requires-Python: >=3.8
Requires-Dist: albumentations>=1.4.23
Requires-Dist: numpy>=2.2.0
Requires-Dist: scikit-image>=0.25.0
Provides-Extra: dev
Requires-Dist: nbstripout>=0.8.1; extra == 'dev'
Requires-Dist: pre-commit>=4.0.1; extra == 'dev'
Requires-Dist: ruff>=0.8.4; extra == 'dev'
Provides-Extra: examples
Requires-Dist: ipympl>=0.9.5; extra == 'examples'
Requires-Dist: ipywidgets>=8.1.5; extra == 'examples'
Requires-Dist: matplotlib>=3.1.0; extra == 'examples'
Requires-Dist: notebook>=7.3.2; extra == 'examples'
